icon_uxarray/__init__.py
icon_uxarray/__main__.py
icon_uxarray/base.py
icon_uxarray/cli.py
icon_uxarray-0.1.8.dist-info/LICENSE
icon_uxarray-0.1.8.dist-info/METADATA
icon_uxarray-0.1.8.dist-info/WHEEL
icon_uxarray-0.1.8.dist-info/entry_points.txt
icon_uxarray-0.1.8.dist-info/top_level.txt
icon_uxarray-0.1.8.dist-info/RECORD
