Metadata-Version: 2.1
Name: icon_uxarray
Version: 0.1.8
Summary: Awesome icon_uxarray created by jcanton
Home-page: https://github.com/jcanton/icon_uxarray/
Author: jcanton
License-File: LICENSE
Requires-Dist: numpy
Requires-Dist: xarray
Requires-Dist: uxarray
Requires-Dist: scipy
Requires-Dist: numba
Requires-Dist: scikit-learn
Requires-Dist: holoviews
Requires-Dist: matplotlib
Requires-Dist: cartopy
Requires-Dist: dask
Requires-Dist: dask[dataframe]
Requires-Dist: datashader
Requires-Dist: netcdf4
Requires-Dist: h5netcdf
Provides-Extra: test
Requires-Dist: pytest ; extra == 'test'
Requires-Dist: coverage ; extra == 'test'
Requires-Dist: flake8 ; extra == 'test'
Requires-Dist: black ; extra == 'test'
Requires-Dist: isort ; extra == 'test'
Requires-Dist: pytest-cov ; extra == 'test'
Requires-Dist: mypy ; extra == 'test'
Requires-Dist: gitchangelog ; extra == 'test'
Requires-Dist: mkdocs ; extra == 'test'
